PyAxe/ACMake.py
PyAxe/ACollection.py
PyAxe/ACommandLineTool.py
PyAxe/ACompress.py
PyAxe/ACore.py
PyAxe/ADebug.py
PyAxe/AElementTree.py
PyAxe/AError.py
PyAxe/AFTP.py
PyAxe/AFile.py
PyAxe/AGit.py
PyAxe/AHash.py
PyAxe/AINI.py
PyAxe/AJenkins.py
PyAxe/ALog.py
PyAxe/AMySQL.py
PyAxe/ANet.py
PyAxe/AOS.py
PyAxe/APyInstaller.py
PyAxe/ARe.py
PyAxe/ASVN.py
PyAxe/AStr.py
PyAxe/ATab.py
PyAxe/AUtil.py
PyAxe/AVEnv.py
PyAxe/AVS.py
PyAxe/AWorkbook.py
PyAxe/__init__.py
pyaxe-1.1.0.dist-info/METADATA
pyaxe-1.1.0.dist-info/WHEEL
pyaxe-1.1.0.dist-info/licenses/LICENSE
pyaxe-1.1.0.dist-info/RECORD
