Metadata-Version: 2.4
Name: PyAxe
Version: 1.1.0
Summary: An utility library for building command-line tool easily
Project-URL: Homepage, https://github.com/sunjinopensource/PyAxe
Project-URL: Bug Tracker, https://github.com/sunjinopensource/PyAxe/issues
Author-email: Sun Jin <412640665@qq.com>
License-File: LICENSE
Classifier: License :: OSI Approved :: MIT License
Classifier: Operating System :: OS Independent
Classifier: Programming Language :: Python :: 3
Requires-Python: >=3.6
